{
  "doc": {
    "nodes": [
      {
        "nodes": [
          {
            "nodes": [],
            "type": "text",
            "key": "7mrho",
            "ricosText": {
              "decorations": [],
              "text": "Leverage agile frameworks to provide a robust synopsis for high level overviews. Iterative approaches to corporate strategy foster collaborative thinking to further the overall value proposition."
            }
          }
        ],
        "type": "paragraph",
        "key": "3icet"
      },
      {
        "nodes": [
          {
            "nodes": [
              {
                "nodes": [
                  {
                    "nodes": [],
                    "type": "text",
                    "key": "fs6ni",
                    "ricosText": {
                      "decorations": [],
                      "text": "Bring to the table win-win survival strategies to ensure proactive domination."
                    }
                  }
                ],
                "type": "paragraph",
                "key": "esq8f"
              }
            ],
            "type": "list_item",
            "key": "d4hhc"
          },
          {
            "nodes": [
              {
                "nodes": [
                  {
                    "nodes": [],
                    "type": "text",
                    "key": "edjc8",
                    "ricosText": {
                      "decorations": [],
                      "text": "At the end of the day, going forward, a new normal that has evolved from generation X is on the runway heading towards a streamlined cloud solution."
                    }
                  }
                ],
                "type": "paragraph",
                "key": "1er78"
              }
            ],
            "type": "list_item",
            "key": "2s6ta"
          }
        ],
        "type": "ordered_list",
        "key": "2cba8"
      },
      {
        "nodes": [
          {
            "nodes": [
              {
                "nodes": [
                  {
                    "nodes": [],
                    "type": "text",
                    "key": "7otbk",
                    "ricosText": {
                      "decorations": [],
                      "text": "Nanotechnology immersion along the information highway will close the loop on focusing solely on the bottom line."
                    }
                  }
                ],
                "type": "paragraph",
                "key": "aoqel"
              }
            ],
            "type": "list_item",
            "key": "dp96d"
          },
          {
            "nodes": [
              {
                "nodes": [
                  {
                    "nodes": [],
                    "type": "text",
                    "key": "21mho",
                    "ricosText": {
                      "decorations": [],
                      "text": "Override the digital divide with additional clickthroughs from DevOps."
                    }
                  }
                ],
                "type": "paragraph",
                "key": "1gi9n"
              }
            ],
            "type": "list_item",
            "key": "7vnq7"
          }
        ],
        "type": "bullet_list",
        "key": "e4qdc"
      },
      {
        "nodes": [
          {
            "nodes": [],
            "type": "text",
            "key": "a8kra",
            "ricosText": {
              "decorations": [],
              "text": "Capitalize on low hanging fruit to identify a ballpark value added activity to beta test."
            }
          }
        ],
        "type": "paragraph",
        "key": "evq3l"
      },
      {
        "nodes": [
          {
            "nodes": [
              {
                "nodes": [
                  {
                    "nodes": [],
                    "type": "text",
                    "key": "8j3p3",
                    "ricosText": {
                      "decorations": [
                        {
                          "type": "bold"
                        }
                      ],
                      "text": "Leverage"
                    }
                  },
                  {
                    "nodes": [],
                    "type": "text",
                    "key": "4g8d5",
                    "ricosText": {
                      "decorations": [],
                      "text": " agile frameworks to provide a robust synopsis for high level overviews. Iterative "
                    }
                  },
                  {
                    "nodes": [],
                    "type": "text",
                    "key": "cku9k",
                    "ricosText": {
                      "decorations": [
                        {
                          "type": "underline"
                        }
                      ],
                      "text": "approaches"
                    }
                  },
                  {
                    "nodes": [],
                    "type": "text",
                    "key": "1pnu5",
                    "ricosText": {
                      "decorations": [],
                      "text": " to corporate strategy foster collaborative thinking to further the overall value proposition."
                    }
                  }
                ],
                "type": "paragraph",
                "key": "2d7o1"
              }
            ],
            "type": "list_item",
            "key": "aaak5"
          },
          {
            "nodes": [
              {
                "nodes": [
                  {
                    "nodes": [],
                    "type": "text",
                    "key": "f0hm0",
                    "ricosText": {
                      "decorations": [],
                      "text": "Bring to the table win-win survival strategies to ensure proactive domination."
                    }
                  }
                ],
                "type": "paragraph",
                "key": "dh39q"
              }
            ],
            "type": "list_item",
            "key": "avm94"
          }
        ],
        "type": "ordered_list",
        "key": "6bbqi"
      },
      {
        "nodes": [
          {
            "nodes": [
              {
                "nodes": [
                  {
                    "nodes": [],
                    "type": "text",
                    "key": "40do7",
                    "ricosText": {
                      "decorations": [
                        {
                          "type": "FG",
                          "ricosColor": {
                            "foreground": "#212121"
                          }
                        }
                      ],
                      "text": "Capitalize on low hanging fruit to identify a ballpark value added activity to beta test."
                    }
                  }
                ],
                "type": "paragraph",
                "key": "cm4bo"
              }
            ],
            "type": "list_item",
            "key": "2r5ci"
          }
        ],
        "type": "bullet_list",
        "key": "13pi0"
      },
      {
        "nodes": [
          {
            "nodes": [
              {
                "nodes": [
                  {
                    "nodes": [],
                    "type": "text",
                    "key": "ebodg",
                    "ricosText": {
                      "decorations": [],
                      "text": "At the end of the day, going "
                    }
                  },
                  {
                    "nodes": [],
                    "type": "text",
                    "key": "22ips",
                    "ricosText": {
                      "decorations": [
                        {
                          "type": "underline"
                        }
                      ],
                      "text": "forward"
                    }
                  },
                  {
                    "nodes": [],
                    "type": "text",
                    "key": "99jd",
                    "ricosText": {
                      "decorations": [],
                      "text": ", a new normal that has evolved from generation X is on the runway heading towards a streamlined cloud solution."
                    }
                  }
                ],
                "type": "paragraph",
                "key": "eu44g"
              }
            ],
            "type": "list_item",
            "key": "91nj7"
          },
          {
            "nodes": [
              {
                "nodes": [
                  {
                    "nodes": [],
                    "type": "text",
                    "key": "98a2b",
                    "ricosText": {
                      "decorations": [
                        {
                          "type": "FG",
                          "ricosColor": {
                            "foreground": "color4"
                          }
                        }
                      ],
                      "text": "Bring to the table win-win survival strategies to ensure proactive domination."
                    }
                  }
                ],
                "type": "paragraph",
                "key": "6cuis"
              }
            ],
            "type": "list_item",
            "key": "biou8"
          },
          {
            "nodes": [
              {
                "nodes": [
                  {
                    "nodes": [],
                    "type": "text",
                    "key": "8corl",
                    "ricosText": {
                      "decorations": [
                        {
                          "type": "FG",
                          "ricosColor": {
                            "foreground": "#212121"
                          }
                        }
                      ],
                      "text": "Capitalize on low hanging fruit to identify a ballpark value added activity to beta test."
                    }
                  }
                ],
                "type": "paragraph",
                "key": "brh9a"
              }
            ],
            "type": "list_item",
            "key": "2qopl"
          }
        ],
        "type": "ordered_list",
        "key": "vk1d"
      },
      {
        "nodes": [
          {
            "nodes": [
              {
                "nodes": [
                  {
                    "nodes": [],
                    "type": "text",
                    "key": "t4t0",
                    "ricosText": {
                      "decorations": [],
                      "text": "Nanotechnology immersion along the information highway will close the loop on focusing solely on the bottom line."
                    }
                  }
                ],
                "type": "paragraph",
                "key": "1eukv"
              }
            ],
            "type": "list_item",
            "key": "fpsut"
          },
          {
            "nodes": [
              {
                "nodes": [
                  {
                    "nodes": [],
                    "type": "text",
                    "key": "a3sjk",
                    "ricosText": {
                      "decorations": [],
                      "text": "Override "
                    }
                  },
                  {
                    "nodes": [],
                    "type": "text",
                    "key": "12uae",
                    "ricosText": {
                      "decorations": [
                        {
                          "type": "BG",
                          "ricosColor": {
                            "background": "color4"
                          }
                        }
                      ],
                      "text": "the digital divide"
                    }
                  },
                  {
                    "nodes": [],
                    "type": "text",
                    "key": "1m9ld",
                    "ricosText": {
                      "decorations": [],
                      "text": " with additional clickthroughs from DevOps."
                    }
                  }
                ],
                "type": "paragraph",
                "key": "e0hp3"
              }
            ],
            "type": "list_item",
            "key": "9tomj"
          }
        ],
        "type": "bullet_list",
        "key": "216f4"
      },
      {
        "nodes": [],
        "type": "paragraph",
        "key": "48p1i"
      }
    ],
    "lastEdited": {
      "seconds": 1608477230,
      "nanos": 967000000
    }
  },
  "selection": {
    "anchorNode": "3icet"
  },
  "version": "7.3.0"
}