{
  "doc": {
    "nodes": [
      {
        "nodes": [
          {
            "nodes": [],
            "type": "text",
            "key": "d7bf1",
            "ricosText": {
              "decorations": [],
              "text": "Leverage agile frameworks to provide a robust synopsis for high level overviews. Iterative approaches to corporate strategy foster collaborative thinking to further the overall value proposition."
            }
          }
        ],
        "type": "paragraph",
        "key": "7jrt6"
      },
      {
        "nodes": [
          {
            "nodes": [
              {
                "nodes": [],
                "type": "text",
                "key": "514up",
                "ricosText": {
                  "decorations": [],
                  "text": "Bring to the table win-win survival strategies to ensure proactive domination."
                }
              }
            ],
            "type": "paragraph",
            "key": "700mb"
          }
        ],
        "type": "blockquote",
        "key": "d4hhc"
      },
      {
        "nodes": [
          {
            "nodes": [],
            "type": "text",
            "key": "9h4vo",
            "ricosText": {
              "decorations": [],
              "text": "At the end of the day, going forward, a new normal that has evolved from generation X is on the runway heading towards a streamlined cloud solution."
            }
          }
        ],
        "type": "paragraph",
        "key": "ah0i1"
      }
    ],
    "lastEdited": {
      "seconds": 1609175506,
      "nanos": 512000000
    }
  },
  "selection": {
    "anchorNode": "7jrt6"
  },
  "version": ""
}