{
  "wix-rich-content-plugin-accordion": 238,
  "wix-rich-content-plugin-button": 256,
  "wix-rich-content-plugin-code-block": 246,
  "wix-rich-content-plugin-divider": 235,
  "wix-rich-content-plugin-emoji": 231,
  "wix-rich-content-plugin-file-upload": 254,
  "wix-rich-content-plugin-gallery": 508,
  "wix-rich-content-plugin-giphy": 236,
  "wix-rich-content-plugin-hashtag": 240,
  "wix-rich-content-plugin-headers-markdown": 230,
  "wix-rich-content-plugin-html": 242,
  "wix-rich-content-plugin-image": 247,
  "wix-rich-content-plugin-indent": 230,
  "wix-rich-content-plugin-line-spacing": 233,
  "wix-rich-content-plugin-link-preview": 247,
  "wix-rich-content-plugin-link": 234,
  "wix-rich-content-plugin-map": 360,
  "wix-rich-content-plugin-mentions": 234,
  "wix-rich-content-plugin-social-polls": 387,
  "wix-rich-content-plugin-sound-cloud": 318,
  "wix-rich-content-plugin-spoiler": 257,
  "wix-rich-content-plugin-table": 307,
  "wix-rich-content-plugin-text-color": 234,
  "wix-rich-content-plugin-undo-redo": 230,
  "wix-rich-content-plugin-vertical-embed": 238,
  "wix-rich-content-plugin-video": 325,
  "rcv": 174,
  "rcv-with-plugins": 242,
  "rcv-with-media-plugins": 603,
  "ricos-viewer": 197,
  "ricos-viewer-no-modal": 197,
  "ricos-viewer-with-plugins": 263,
  "rce": 741,
  "rce-with-plugins": 953,
  "ricos-editor": 792,
  "ricos-editor-no-modal": 792,
  "ricos-editor-with-plugins": 1004,
  "ricos-common": 17,
  "ricos-content": 49,
  "rich-content-schema": 70,
  "converters": 318,
  "editor-common": 436
}
